{
  "routes": {
    "1762337458399": {
      "routes": [
        {
          "idx": 0,
          "duration": 8446.6,
          "distance": 138783.2,
          "geometry": {
            "coordinates": [
              [
                -44.87373,
                -20.15977
              ],
              [
                -44.87484,
                -20.15769
              ],
              [
                -44.87696,
                -20.1545
              ],
              [
                -44.87893,
                -20.14989
              ],
              [
                -44.87994,
                -20.14931
              ],
              [
                -44.8794,
                -20.14719
              ],
              [
                -44.87796,
                -20.14661
              ],
              [
                -44.87773,
                -20.14661
              ],
              [
                -44.87768,
                -20.14643
              ],
              [
                -44.87799,
                -20.14556
              ],
              [
                -44.87816,
                -20.14468
              ],
              [
                -44.87853,
                -20.14319
              ],
              [
                -44.87655,
                -20.14117
              ],
              [
                -44.87219,
                -20.13905
              ],
              [
                -44.87192,
                -20.13756
              ],
              [
                -44.87165,
                -20.13504
              ],
              [
                -44.86975,
                -20.13332
              ],
              [
                -44.86868,
                -20.13318
              ],
              [
                -44.86503,
                -20.13257
              ],
              [
                -44.8626,
                -20.13209
              ],
              [
                -44.86187,
                -20.13146
              ],
              [
                -44.86162,
                -20.13052
              ],
              [
                -44.86171,
                -20.12876
              ],
              [
                -44.86168,
                -20.12749
              ],
              [
                -44.8609,
                -20.12597
              ],
              [
                -44.86004,
                -20.12406
              ],
              [
                -44.85904,
                -20.11894
              ],
              [
                -44.85846,
                -20.11728
              ],
              [
                -44.8564,
                -20.11564
              ],
              [
                -44.85588,
                -20.11548
              ],
              [
                -44.85569,
                -20.11527
              ],
              [
                -44.85507,
                -20.11465
              ],
              [
                -44.85243,
                -20.11279
              ],
              [
                -44.85107,
                -20.11192
              ],
              [
                -44.84879,
                -20.11036
              ],
              [
                -44.84758,
                -20.10988
              ],
              [
                -44.84672,
                -20.10933
              ],
              [
                -44.84488,
                -20.10827
              ],
              [
                -44.84224,
                -20.10567
              ],
              [
                -44.83913,
                -20.10238
              ],
              [
                -44.83856,
                -20.1007
              ],
              [
                -44.83826,
                -20.09941
              ],
              [
                -44.83689,
                -20.09815
              ],
              [
                -44.83537,
                -20.09786
              ],
              [
                -44.83415,
                -20.09739
              ],
              [
                -44.83109,
                -20.09488
              ],
              [
                -44.82791,
                -20.0916
              ],
              [
                -44.82732,
                -20.09
              ],
              [
                -44.82567,
                -20.08583
              ],
              [
                -44.82443,
                -20.0842
              ],
              [
                -44.82294,
                -20.08259
              ],
              [
                -44.82153,
                -20.08142
              ],
              [
                -44.8193,
                -20.08
              ],
              [
                -44.81714,
                -20.07933
              ],
              [
                -44.80802,
                -20.07784
              ],
              [
                -44.80455,
                -20.07741
              ],
              [
                -44.80294,
                -20.07811
              ],
              [
                -44.80046,
                -20.07976
              ],
              [
                -44.79805,
                -20.08063
              ],
              [
                -44.79334,
                -20.08114
              ],
              [
                -44.79037,
                -20.08123
              ],
              [
                -44.78886,
                -20.08071
              ],
              [
                -44.78612,
                -20.07922
              ],
              [
                -44.78464,
                -20.07875
              ],
              [
                -44.78273,
                -20.07843
              ],
              [
                -44.77727,
                -20.0775
              ],
              [
                -44.77212,
                -20.07663
              ],
              [
                -44.77036,
                -20.07632
              ],
              [
                -44.76263,
                -20.07506
              ],
              [
                -44.75281,
                -20.08005
              ],
              [
                -44.7489,
                -20.08217
              ],
              [
                -44.74752,
                -20.08229
              ],
              [
                -44.74613,
                -20.08188
              ],
              [
                -44.74156,
                -20.07827
              ],
              [
                -44.73757,
                -20.07557
              ],
              [
                -44.72672,
                -20.07502
              ],
              [
                -44.72099,
                -20.07482
              ],
              [
                -44.71561,
                -20.0746
              ],
              [
                -44.71304,
                -20.0743
              ],
              [
                -44.71114,
                -20.07333
              ],
              [
                -44.70961,
                -20.07228
              ],
              [
                -44.7077,
                -20.07174
              ],
              [
                -44.70413,
                -20.07135
              ],
              [
                -44.70102,
                -20.07103
              ],
              [
                -44.69841,
                -20.07075
              ],
              [
                -44.69473,
                -20.07035
              ],
              [
                -44.69114,
                -20.06995
              ],
              [
                -44.687,
                -20.06949
              ],
              [
                -44.67885,
                -20.06863
              ],
              [
                -44.67163,
                -20.06786
              ],
              [
                -44.66664,
                -20.0673
              ],
              [
                -44.66436,
                -20.06712
              ],
              [
                -44.6633,
                -20.06732
              ],
              [
                -44.66244,
                -20.06728
              ],
              [
                -44.6608,
                -20.06728
              ],
              [
                -44.65297,
                -20.0719
              ],
              [
                -44.64704,
                -20.07533
              ],
              [
                -44.64518,
                -20.07591
              ],
              [
                -44.64305,
                -20.07618
              ],
              [
                -44.64012,
                -20.07625
              ],
              [
                -44.63782,
                -20.07603
              ],
              [
                -44.63685,
                -20.07524
              ],
              [
                -44.63543,
                -20.07334
              ],
              [
                -44.6341,
                -20.07241
              ],
              [
                -44.62987,
                -20.07122
              ],
              [
                -44.62711,
                -20.07145
              ],
              [
                -44.62324,
                -20.07201
              ],
              [
                -44.62161,
                -20.07148
              ],
              [
                -44.61881,
                -20.07024
              ],
              [
                -44.61354,
                -20.06769
              ],
              [
                -44.61237,
                -20.06629
              ],
              [
                -44.61202,
                -20.06525
              ],
              [
                -44.61185,
                -20.06227
              ],
              [
                -44.61149,
                -20.0607
              ],
              [
                -44.61066,
                -20.0602
              ],
              [
                -44.60918,
                -20.06037
              ],
              [
                -44.60774,
                -20.0608
              ],
              [
                -44.60582,
                -20.06136
              ],
              [
                -44.60473,
                -20.06115
              ],
              [
                -44.60246,
                -20.05996
              ],
              [
                -44.60059,
                -20.06013
              ],
              [
                -44.59709,
                -20.06093
              ],
              [
                -44.59454,
                -20.06148
              ],
              [
                -44.58466,
                -20.06357
              ],
              [
                -44.58044,
                -20.0645
              ],
              [
                -44.57868,
                -20.06453
              ],
              [
                -44.57567,
                -20.06374
              ],
              [
                -44.57412,
                -20.06282
              ],
              [
                -44.57283,
                -20.0625
              ],
              [
                -44.57023,
                -20.06277
              ],
              [
                -44.56636,
                -20.06214
              ],
              [
                -44.56337,
                -20.06207
              ],
              [
                -44.55782,
                -20.06265
              ],
              [
                -44.55674,
                -20.0626
              ],
              [
                -44.55625,
                -20.0625
              ],
              [
                -44.55492,
                -20.06196
              ],
              [
                -44.54921,
                -20.05944
              ],
              [
                -44.54717,
                -20.05834
              ],
              [
                -44.54588,
                -20.05709
              ],
              [
                -44.54414,
                -20.05438
              ],
              [
                -44.54022,
                -20.048
              ],
              [
                -44.5387,
                -20.04552
              ],
              [
                -44.53685,
                -20.04292
              ],
              [
                -44.53323,
                -20.03985
              ],
              [
                -44.53215,
                -20.03881
              ],
              [
                -44.53036,
                -20.03707
              ],
              [
                -44.52945,
                -20.03645
              ],
              [
                -44.52825,
                -20.03649
              ],
              [
                -44.5262,
                -20.037
              ],
              [
                -44.52536,
                -20.03683
              ],
              [
                -44.52459,
                -20.0358
              ],
              [
                -44.52246,
                -20.03173
              ],
              [
                -44.52024,
                -20.02992
              ],
              [
                -44.51792,
                -20.02817
              ],
              [
                -44.51653,
                -20.02766
              ],
              [
                -44.5125,
                -20.02723
              ],
              [
                -44.51076,
                -20.02714
              ],
              [
                -44.50928,
                -20.02653
              ],
              [
                -44.50456,
                -20.02549
              ],
              [
                -44.50204,
                -20.02381
              ],
              [
                -44.49967,
                -20.02156
              ],
              [
                -44.49643,
                -20.01969
              ],
              [
                -44.48977,
                -20.01605
              ],
              [
                -44.487,
                -20.01468
              ],
              [
                -44.48513,
                -20.01414
              ],
              [
                -44.48219,
                -20.01364
              ],
              [
                -44.48001,
                -20.01283
              ],
              [
                -44.47771,
                -20.01226
              ],
              [
                -44.47532,
                -20.01166
              ],
              [
                -44.47348,
                -20.01119
              ],
              [
                -44.47229,
                -20.0105
              ],
              [
                -44.47124,
                -20.00898
              ],
              [
                -44.47008,
                -20.00695
              ],
              [
                -44.46923,
                -20.00552
              ],
              [
                -44.46799,
                -20.00404
              ],
              [
                -44.46585,
                -20.00359
              ],
              [
                -44.46124,
                -20.00365
              ],
              [
                -44.45828,
                -20.00273
              ],
              [
                -44.45495,
                -20.00124
              ],
              [
                -44.45266,
                -20.00167
              ],
              [
                -44.44973,
                -20.00066
              ],
              [
                -44.44547,
                -19.99875
              ],
              [
                -44.44163,
                -19.99707
              ],
              [
                -44.4366,
                -19.99482
              ],
              [
                -44.43415,
                -19.99381
              ],
              [
                -44.42707,
                -19.99182
              ],
              [
                -44.41589,
                -19.98874
              ],
              [
                -44.40844,
                -19.9865
              ],
              [
                -44.39881,
                -19.98215
              ],
              [
                -44.39635,
                -19.98139
              ],
              [
                -44.3913,
                -19.98177
              ],
              [
                -44.38973,
                -19.981
              ],
              [
                -44.38744,
                -19.97891
              ],
              [
                -44.38347,
                -19.97523
              ],
              [
                -44.38109,
                -19.97404
              ],
              [
                -44.37524,
                -19.97199
              ],
              [
                -44.36367,
                -19.96793
              ],
              [
                -44.35846,
                -19.96806
              ],
              [
                -44.35062,
                -19.96889
              ],
              [
                -44.34931,
                -19.96853
              ],
              [
                -44.34738,
                -19.96673
              ],
              [
                -44.34393,
                -19.96331
              ],
              [
                -44.34173,
                -19.9616
              ],
              [
                -44.33827,
                -19.96019
              ],
              [
                -44.33712,
                -19.96053
              ],
              [
                -44.3366,
                -19.96103
              ],
              [
                -44.33524,
                -19.96253
              ],
              [
                -44.33416,
                -19.96424
              ],
              [
                -44.33349,
                -19.96639
              ],
              [
                -44.3328,
                -19.9679
              ],
              [
                -44.33019,
                -19.97212
              ],
              [
                -44.32906,
                -19.97338
              ],
              [
                -44.32783,
                -19.97418
              ],
              [
                -44.32618,
                -19.97472
              ],
              [
                -44.32403,
                -19.97473
              ],
              [
                -44.3215,
                -19.97438
              ],
              [
                -44.31808,
                -19.97383
              ],
              [
                -44.31469,
                -19.97332
              ],
              [
                -44.31046,
                -19.97267
              ],
              [
                -44.30757,
                -19.97226
              ],
              [
                -44.30571,
                -19.97252
              ],
              [
                -44.30369,
                -19.97348
              ],
              [
                -44.30249,
                -19.97361
              ],
              [
                -44.29897,
                -19.97237
              ],
              [
                -44.29619,
                -19.97139
              ],
              [
                -44.29335,
                -19.97052
              ],
              [
                -44.29012,
                -19.97081
              ],
              [
                -44.28678,
                -19.97136
              ],
              [
                -44.28339,
                -19.97193
              ],
              [
                -44.28094,
                -19.97234
              ],
              [
                -44.27737,
                -19.97293
              ],
              [
                -44.2733,
                -19.97359
              ],
              [
                -44.26987,
                -19.97398
              ],
              [
                -44.26861,
                -19.97379
              ],
              [
                -44.26632,
                -19.97313
              ],
              [
                -44.26409,
                -19.97337
              ],
              [
                -44.26054,
                -19.97522
              ],
              [
                -44.25836,
                -19.97647
              ],
              [
                -44.25378,
                -19.97864
              ],
              [
                -44.25229,
                -19.97961
              ],
              [
                -44.25056,
                -19.98025
              ],
              [
                -44.24428,
                -19.9835
              ],
              [
                -44.24155,
                -19.98435
              ],
              [
                -44.23817,
                -19.9839
              ],
              [
                -44.23547,
                -19.98331
              ],
              [
                -44.23009,
                -19.98192
              ],
              [
                -44.22588,
                -19.98016
              ],
              [
                -44.22283,
                -19.9789
              ],
              [
                -44.22046,
                -19.9784
              ],
              [
                -44.21633,
                -19.97943
              ],
              [
                -44.21263,
                -19.98053
              ],
              [
                -44.21056,
                -19.98207
              ],
              [
                -44.20817,
                -19.98393
              ],
              [
                -44.20341,
                -19.98577
              ],
              [
                -44.20139,
                -19.98667
              ],
              [
                -44.19914,
                -19.98794
              ],
              [
                -44.19685,
                -19.98832
              ],
              [
                -44.19455,
                -19.98939
              ],
              [
                -44.19262,
                -19.98994
              ],
              [
                -44.19047,
                -19.98988
              ],
              [
                -44.18574,
                -19.98791
              ],
              [
                -44.18403,
                -19.98732
              ],
              [
                -44.1768,
                -19.98688
              ],
              [
                -44.16991,
                -19.98653
              ],
              [
                -44.16762,
                -19.98517
              ],
              [
                -44.16351,
                -19.98213
              ],
              [
                -44.16057,
                -19.97958
              ],
              [
                -44.1604,
                -19.97448
              ],
              [
                -44.15989,
                -19.96928
              ],
              [
                -44.15895,
                -19.96559
              ],
              [
                -44.15722,
                -19.96318
              ],
              [
                -44.15397,
                -19.96066
              ],
              [
                -44.14954,
                -19.95737
              ],
              [
                -44.14761,
                -19.95637
              ],
              [
                -44.14625,
                -19.95607
              ],
              [
                -44.14256,
                -19.95633
              ],
              [
                -44.13891,
                -19.95677
              ],
              [
                -44.13719,
                -19.95669
              ],
              [
                -44.13345,
                -19.95617
              ],
              [
                -44.13,
                -19.95589
              ],
              [
                -44.12718,
                -19.95649
              ],
              [
                -44.12178,
                -19.95778
              ],
              [
                -44.11987,
                -19.9575
              ],
              [
                -44.1174,
                -19.95549
              ],
              [
                -44.11511,
                -19.95555
              ],
              [
                -44.11227,
                -19.95579
              ],
              [
                -44.11028,
                -19.95593
              ],
              [
                -44.10792,
                -19.95607
              ],
              [
                -44.10538,
                -19.95616
              ],
              [
                -44.10328,
                -19.95615
              ],
              [
                -44.09781,
                -19.95566
              ],
              [
                -44.09627,
                -19.95572
              ],
              [
                -44.09519,
                -19.95612
              ],
              [
                -44.09258,
                -19.95784
              ],
              [
                -44.08986,
                -19.95931
              ],
              [
                -44.08702,
                -19.95958
              ],
              [
                -44.08241,
                -19.95975
              ],
              [
                -44.08099,
                -19.95925
              ],
              [
                -44.07979,
                -19.95799
              ],
              [
                -44.07857,
                -19.9576
              ],
              [
                -44.07527,
                -19.95869
              ],
              [
                -44.07365,
                -19.95899
              ],
              [
                -44.06623,
                -19.95901
              ],
              [
                -44.06116,
                -19.95865
              ],
              [
                -44.05644,
                -19.9582
              ],
              [
                -44.05493,
                -19.95884
              ],
              [
                -44.05315,
                -19.96006
              ],
              [
                -44.05042,
                -19.96202
              ],
              [
                -44.04791,
                -19.96375
              ],
              [
                -44.0465,
                -19.96424
              ],
              [
                -44.04529,
                -19.96435
              ],
              [
                -44.04366,
                -19.96411
              ],
              [
                -44.03851,
                -19.96176
              ],
              [
                -44.03476,
                -19.96005
              ],
              [
                -44.03307,
                -19.95928
              ],
              [
                -44.02991,
                -19.9578
              ],
              [
                -44.02632,
                -19.95617
              ],
              [
                -44.0205,
                -19.95344
              ],
              [
                -44.01437,
                -19.95067
              ],
              [
                -44.01034,
                -19.94878
              ],
              [
                -44.00721,
                -19.9473
              ],
              [
                -44.00631,
                -19.94656
              ],
              [
                -44.00757,
                -19.94493
              ],
              [
                -44.00783,
                -19.94317
              ],
              [
                -44.00766,
                -19.93931
              ],
              [
                -44.00755,
                -19.93661
              ],
              [
                -44.00732,
                -19.93166
              ],
              [
                -44.00616,
                -19.92681
              ],
              [
                -44.00479,
                -19.92393
              ],
              [
                -44.00018,
                -19.9205
              ],
              [
                -43.99557,
                -19.91671
              ],
              [
                -43.99359,
                -19.91415
              ],
              [
                -43.99368,
                -19.91297
              ],
              [
                -43.99422,
                -19.91044
              ],
              [
                -43.99317,
                -19.90886
              ],
              [
                -43.9854,
                -19.90357
              ],
              [
                -43.98351,
                -19.90215
              ],
              [
                -43.97929,
                -19.89489
              ],
              [
                -43.97823,
                -19.89348
              ],
              [
                -43.97512,
                -19.89158
              ],
              [
                -43.97181,
                -19.88931
              ],
              [
                -43.9695,
                -19.88751
              ],
              [
                -43.96656,
                -19.88526
              ],
              [
                -43.96225,
                -19.88327
              ],
              [
                -43.95558,
                -19.8811
              ],
              [
                -43.95355,
                -19.88012
              ],
              [
                -43.95104,
                -19.87704
              ],
              [
                -43.94956,
                -19.87463
              ],
              [
                -43.94765,
                -19.8711
              ],
              [
                -43.94617,
                -19.87025
              ],
              [
                -43.94317,
                -19.86991
              ],
              [
                -43.93646,
                -19.86802
              ],
              [
                -43.93357,
                -19.86738
              ],
              [
                -43.931,
                -19.86683
              ],
              [
                -43.92995,
                -19.86643
              ],
              [
                -43.92885,
                -19.866
              ],
              [
                -43.9286,
                -19.86644
              ],
              [
                -43.92904,
                -19.86673
              ],
              [
                -43.93068,
                -19.86489
              ],
              [
                -43.93077,
                -19.86443
              ],
              [
                -43.93012,
                -19.86424
              ],
              [
                -43.9295,
                -19.86431
              ],
              [
                -43.92935,
                -19.86452
              ],
              [
                -43.92876,
                -19.86425
              ],
              [
                -43.92853,
                -19.86408
              ],
              [
                -43.92838,
                -19.86394
              ],
              [
                -43.92757,
                -19.86343
              ],
              [
                -43.92662,
                -19.86205
              ],
              [
                -43.92493,
                -19.86092
              ],
              [
                -43.92443,
                -19.85998
              ],
              [
                -43.92382,
                -19.85757
              ],
              [
                -43.92272,
                -19.85495
              ],
              [
                -43.92002,
                -19.85013
              ],
              [
                -43.91845,
                -19.84845
              ],
              [
                -43.91556,
                -19.84634
              ],
              [
                -43.91498,
                -19.84581
              ],
              [
                -43.91387,
                -19.8445
              ],
              [
                -43.91243,
                -19.84318
              ],
              [
                -43.91145,
                -19.84178
              ],
              [
                -43.90882,
                -19.83802
              ],
              [
                -43.90717,
                -19.83543
              ],
              [
                -43.9065,
                -19.83407
              ],
              [
                -43.90468,
                -19.83234
              ],
              [
                -43.90336,
                -19.82993
              ],
              [
                -43.9044,
                -19.82755
              ],
              [
                -43.90517,
                -19.82611
              ],
              [
                -43.9048,
                -19.82433
              ],
              [
                -43.90286,
                -19.822
              ],
              [
                -43.90121,
                -19.8201
              ],
              [
                -43.9003,
                -19.81996
              ],
              [
                -43.89797,
                -19.8205
              ],
              [
                -43.89545,
                -19.82052
              ],
              [
                -43.89306,
                -19.82162
              ],
              [
                -43.89198,
                -19.8218
              ],
              [
                -43.89018,
                -19.81967
              ],
              [
                -43.88808,
                -19.81871
              ],
              [
                -43.88623,
                -19.81724
              ],
              [
                -43.88491,
                -19.81543
              ],
              [
                -43.88461,
                -19.81461
              ],
              [
                -43.88462,
                -19.81383
              ],
              [
                -43.88489,
                -19.8127
              ],
              [
                -43.88505,
                -19.81064
              ],
              [
                -43.88492,
                -19.80982
              ],
              [
                -43.88516,
                -19.8094
              ],
              [
                -43.88484,
                -19.80755
              ],
              [
                -43.88415,
                -19.80613
              ],
              [
                -43.88241,
                -19.80427
              ],
              [
                -43.88058,
                -19.80272
              ],
              [
                -43.88022,
                -19.80196
              ],
              [
                -43.88062,
                -19.80067
              ],
              [
                -43.88079,
                -19.7996
              ],
              [
                -43.88047,
                -19.7983
              ],
              [
                -43.87932,
                -19.79628
              ],
              [
                -43.87896,
                -19.79326
              ],
              [
                -43.87879,
                -19.793
              ],
              [
                -43.87882,
                -19.79275
              ],
              [
                -43.8787,
                -19.79117
              ],
              [
                -43.87803,
                -19.78974
              ],
              [
                -43.87742,
                -19.78865
              ],
              [
                -43.8774,
                -19.7879
              ],
              [
                -43.87697,
                -19.78747
              ],
              [
                -43.87647,
                -19.7866
              ],
              [
                -43.87639,
                -19.78561
              ],
              [
                -43.87571,
                -19.78462
              ],
              [
                -43.87431,
                -19.78342
              ],
              [
                -43.87277,
                -19.78149
              ],
              [
                -43.87166,
                -19.78053
              ],
              [
                -43.87033,
                -19.7797
              ],
              [
                -43.86998,
                -19.77951
              ],
              [
                -43.87001,
                -19.77927
              ],
              [
                -43.86989,
                -19.77786
              ],
              [
                -43.86944,
                -19.77567
              ],
              [
                -43.86929,
                -19.77555
              ],
              [
                -43.8678,
                -19.77542
              ],
              [
                -43.86718,
                -19.77505
              ],
              [
                -43.86696,
                -19.77501
              ],
              [
                -43.8669,
                -19.7747
              ],
              [
                -43.86647,
                -19.77285
              ],
              [
                -43.86526,
                -19.77276
              ],
              [
                -43.86192,
                -19.77256
              ],
              [
                -43.86059,
                -19.77213
              ],
              [
                -43.8597,
                -19.7725
              ],
              [
                -43.85879,
                -19.77385
              ],
              [
                -43.85864,
                -19.77386
              ],
              [
                -43.85825,
                -19.77379
              ],
              [
                -43.85743,
                -19.77379
              ],
              [
                -43.85696,
                -19.77267
              ],
              [
                -43.85636,
                -19.77105
              ],
              [
                -43.85453,
                -19.76961
              ],
              [
                -43.85092,
                -19.77012
              ],
              [
                -43.85054,
                -19.77011
              ]
            ],
            "type": "LineString"
          },
          "delta_sec": 0
        }
      ],
      "activeIndex": 0,
      "timestamp": "2025-11-05T20:39:51.651Z"
    }
  }
}